md2weasypdf/__init__.py
md2weasypdf/__main__.py
md2weasypdf/printer.py
md2weasypdf/extensions/__init__.py
md2weasypdf/extensions/checkbox.py
md2weasypdf/extensions/footnotes.py
md2weasypdf/extensions/mermaid.py
md2weasypdf/extensions/subscript.py
md2weasypdf/extensions/superscript.py
md2weasypdf/extensions/table_caption.py
md2weasypdf/extensions/textbox.py
md2weasypdf/extensions/toa.py
md2weasypdf/extensions/toc.py
md2weasypdf-0.0.48.dist-info/licenses/LICENSE
md2weasypdf-0.0.48.dist-info/METADATA
md2weasypdf-0.0.48.dist-info/WHEEL
md2weasypdf-0.0.48.dist-info/top_level.txt
md2weasypdf-0.0.48.dist-info/RECORD
