Metadata-Version: 2.4
Name: md2weasypdf
Version: 0.0.48
Summary: Print PDFs from Markdown Files using Weasyprint
Home-page: https://github.com/mstingl/md2weasypdf
Author: Manuel Stingl
Author-email: contact@stingl.st
License: GNU LGPLv2.1
Classifier: Programming Language :: Python :: 3
Classifier: License :: OSI Approved :: GNU Lesser General Public License v2 or later (LGPLv2+)
Classifier: Operating System :: OS Independent
Requires-Python: >=3.9
License-File: LICENSE
Requires-Dist: typer
Requires-Dist: rich
Requires-Dist: weasyprint==65.1
Requires-Dist: markdown
Requires-Dist: jinja2
Requires-Dist: watchdog
Requires-Dist: markdown-grid-tables
Requires-Dist: python-frontmatter
Requires-Dist: pyyaml
Requires-Dist: lxml
Requires-Dist: jsonschema
Dynamic: license-file
